accelbyte_py_sdk/api/session/__init__.py
accelbyte_py_sdk/api/session/errors.py
accelbyte_py_sdk/api/session/models/__init__.py
accelbyte_py_sdk/api/session/models/apimodels_append_team_game_session_request.py
accelbyte_py_sdk/api/session/models/apimodels_config_alert_request_create.py
accelbyte_py_sdk/api/session/models/apimodels_config_alert_response.py
accelbyte_py_sdk/api/session/models/apimodels_configuration_template_response.py
accelbyte_py_sdk/api/session/models/apimodels_configuration_templates_response.py
accelbyte_py_sdk/api/session/models/apimodels_create_configuration_template_request.py
accelbyte_py_sdk/api/session/models/apimodels_create_game_session_request.py
accelbyte_py_sdk/api/session/models/apimodels_create_party_request.py
accelbyte_py_sdk/api/session/models/apimodels_delete_bulk_game_session_request.py
accelbyte_py_sdk/api/session/models/apimodels_delete_bulk_game_sessions_api_response.py
accelbyte_py_sdk/api/session/models/apimodels_delete_bulk_party_session_request.py
accelbyte_py_sdk/api/session/models/apimodels_delete_bulk_party_sessions_api_response.py
accelbyte_py_sdk/api/session/models/apimodels_ds_information_response.py
accelbyte_py_sdk/api/session/models/apimodels_environment_variable_list_response.py
accelbyte_py_sdk/api/session/models/apimodels_environment_variable_response.py
accelbyte_py_sdk/api/session/models/apimodels_game_session_query_response.py
accelbyte_py_sdk/api/session/models/apimodels_game_session_response.py
accelbyte_py_sdk/api/session/models/apimodels_global_configuration_response.py
accelbyte_py_sdk/api/session/models/apimodels_join_by_code_request.py
accelbyte_py_sdk/api/session/models/apimodels_kick_response.py
accelbyte_py_sdk/api/session/models/apimodels_native_session_paging_response.py
accelbyte_py_sdk/api/session/models/apimodels_pagination.py
accelbyte_py_sdk/api/session/models/apimodels_party_query_response.py
accelbyte_py_sdk/api/session/models/apimodels_party_session_response.py
accelbyte_py_sdk_service_session-0.28.0.dist-info/METADATA
accelbyte_py_sdk_service_session-0.28.0.dist-info/WHEEL
accelbyte_py_sdk_service_session-0.28.0.dist-info/top_level.txt
accelbyte_py_sdk_service_session-0.28.0.dist-info/RECORD
